{"wood_pieces":6,"cards_deck":29,"i_b_percent":[25,50,25],"mode":"puzzle","i_b_time":19,"i_b_strength":[2,2],"tasks_values":[1,6,13],"i_b_moves":4,"cards":[[0,159,261,0,false,false,[],0,"wax"],[1,69,291,0,false,false,[],0,"wax_cure"],[2,729,291,0,false,false,[],0,"wax_cure"],[3,639,261,0,false,false,[],0,"wax"],[4,189,141,30,false,false,[],0,"wax"],[5,609,141,-30,false,false,[],0,"wax"],[6,279,51,60,false,false,[],0,"wax"],[7,519,51,-60,false,false,[],0,"wax"],[8,399,21,90,true,true,[],0,"wood"],[9,144,51,30,false,false,[],0,"wax_cure"],[10,654,51,-30,false,false,[],0,"wax_cure"],[11,9,96,-60,true,true,[],0,"goal"],[12,789,96,60,true,true,[],0,"goal"],[13,84,171,15,false,false,[],0,"wax_cure"],[14,714,171,-15,false,false,[],0,"wax_cure"],[15,264,291,-75,false,false,[],0,"none"],[16,534,291,75,false,false,[],0,"none"],[17,324,156,-30,false,false,[],0,"none"],[18,474,156,30,false,false,[],0,"none"],[19,399,306,0,false,false,[],0,"none"],[20,99,276,0,false,false,[13,1,0],1,"wax_cure"],[21,699,276,0,false,false,[14,3,2],1,"wax_cure"],[22,84,186,-90,false,false,[13,11,4,0],1,"wax_cure"],[23,714,186,90,false,false,[14,5,3],1,"wax_cure"],[24,189,6,30,false,false,[9],1,"none"],[25,609,6,-30,false,false,[10],1,"none"],[26,324,36,75,true,true,[8,6],1,"wood"],[27,474,36,-75,true,true,[8,7],1,"wood"],[28,54,51,-45,true,true,[13,11,9],1,"ice"],[29,744,51,45,true,true,[14,12,10],1,"ice"],[30,324,306,-75,false,false,[19,15],1,"wax_cure"],[31,474,306,75,false,false,[19,16],1,"wax_cure"],[32,294,186,-45,false,false,[17],1,"none"],[33,504,186,45,false,false,[18],1,"none"],[34,174,246,0,false,false,[15,4,0],1,"wax"],[35,219,111,30,false,false,[6,4],1,"wax"],[36,579,111,-30,false,false,[7,5],1,"wax"],[37,624,246,0,false,false,[16,5,3],1,"wax"],[38,399,141,0,false,false,[18,17],1,"none"],[39,99,21,-30,true,true,[28,24],2,"ice"],[40,699,21,30,true,true,[29,25],2,"ice"],[41,234,291,-75,false,false,[34,30],2,"none"],[42,564,291,75,false,false,[37,31],2,"none"],[43,189,156,15,false,false,[35,34],2,"wax"],[44,609,156,-15,false,false,[37,36],2,"wax"],[45,129,261,0,false,false,[34,22,20],2,"wax_cure"],[46,669,261,0,false,false,[37,23,21],2,"wax_cure"],[47,234,51,-60,false,false,[35,26,24],2,"wax"],[48,564,51,60,false,false,[36,27,25],2,"wax"],[49,69,141,0,false,false,[28,22],2,"none"],[50,729,141,0,false,false,[29,23],2,"none"],[51,399,21,0,true,true,[27,26],2,"wood"],[52,279,216,-60,false,false,[32,30],2,"wax_cure"],[53,519,216,60,false,false,[33,31],2,"wax_cure"],[54,399,171,90,false,false,[38,33,32],2,"none"],[55,399,291,0,false,false,[31,30],2,"none"],[56,144,0,-15,true,true,[47,39],3,"ice"],[57,654,0,15,true,true,[48,40],3,"ice"],[58,69,111,0,true,true,[49,39],3,"ice"],[59,729,111,0,true,true,[50,40],3,"ice"],[60,639,246,-15,false,false,[46,44,42],3,"wax"],[61,159,246,15,false,false,[45,43,41],3,"wax"],[62,234,81,30,false,false,[47,43],3,"wax"],[63,564,81,-30,false,false,[48,44],3,"wax"],[64,534,246,75,false,false,[53,42],3,"wax_cure"],[65,264,246,-75,false,false,[52,41],3,"wax_cure"],[66,339,156,-15,false,false,[54,52],3,"ice_cure"],[67,459,156,15,false,false,[54,53],3,"ice_cure"],[68,339,6,-15,true,true,[51],3,"wood"],[69,459,6,15,true,true,[51],3,"wood"],[70,399,276,0,false,false,[55],3,"none"],[71,399,141,0,false,false,[67,66],4,"ice_cure"],[72,294,186,-45,false,false,[66,65],4,"none"],[73,504,186,45,false,false,[67,64],4,"none"],[74,189,0,0,true,true,[62,56],4,"ice"],[75,609,0,0,true,true,[63,57],4,"ice"],[76,84,81,15,true,true,[58,56],4,"ice"],[77,714,81,-15,true,true,[59,57],4,"ice"],[78,204,201,-45,false,false,[65,61],4,"none"],[79,594,201,45,false,false,[64,60],4,"none"],[80,399,0,0,true,true,[69,68],4,"wood"],[81,399,261,0,false,false,[70],4,"none"],[82,399,186,90,true,true,[81,73,72,71],5,"none"],[83,264,231,-60,true,true,[78,72],5,"none"],[84,534,231,60,true,true,[79,73],5,"none"]],"tasks":[0,3,4]}