{"wood_pieces":7,"cards_deck":35,"i_b_percent":[25,30,45],"mode":"puzzle","i_b_time":27,"i_b_strength":[2,2],"tasks_values":[1,12],"i_b_moves":3,"cards":[[0,774,306,0,false,false,[],0,"wax_cure"],[1,24,306,0,false,false,[],0,"wax_cure"],[2,24,6,0,false,false,[],0,"wax_cure"],[3,774,6,0,false,false,[],0,"wax_cure"],[4,264,306,0,false,false,[],0,"none"],[5,264,6,0,false,false,[],0,"none"],[6,534,6,0,false,false,[],0,"none"],[7,534,306,0,false,false,[],0,"none"],[8,264,126,0,false,false,[],0,"none"],[9,534,126,0,false,false,[],0,"none"],[10,339,111,0,true,true,[],0,"goal"],[11,459,111,0,true,true,[],0,"goal"],[12,339,231,0,true,true,[],0,"goal"],[13,459,231,0,true,true,[],0,"goal"],[14,39,291,0,false,false,[1],1,"wax_cure"],[15,759,291,0,false,false,[0],1,"none"],[16,39,21,0,false,false,[2],1,"wax_cure"],[17,759,21,0,false,false,[3],1,"none"],[18,249,21,0,false,false,[8,5],1,"wax_cure"],[19,549,21,0,false,false,[9,6],1,"none"],[20,249,291,0,false,false,[4],1,"wax_cure"],[21,549,291,0,false,false,[7],1,"none"],[22,249,141,0,false,false,[8],1,"wax_cure"],[23,549,141,0,false,false,[9],1,"wood"],[24,324,36,0,true,true,[10,8,5],1,"wax"],[25,474,36,0,true,true,[11,9,6],1,"wax"],[26,399,36,0,true,true,[11,10],1,"wax"],[27,474,306,0,true,true,[13,7],1,"wax"],[28,399,306,0,true,true,[13,12],1,"wax"],[29,324,306,0,true,true,[12,4],1,"wax"],[30,324,171,0,false,false,[12,10,8],1,"wax"],[31,399,171,0,false,false,[13,12,11,10],1,"wax"],[32,474,171,0,false,false,[13,11,9],1,"wax"],[33,54,36,0,false,false,[16],2,"cobweb"],[34,54,276,0,false,false,[14],2,"cobweb"],[35,744,36,0,false,false,[17],2,"cobweb"],[36,744,276,0,false,false,[15],2,"cobweb"],[37,234,36,0,false,false,[22,18],2,"cobweb"],[38,564,36,0,false,false,[23,19],2,"none"],[39,234,276,0,false,false,[20],2,"none"],[40,564,276,0,false,false,[21],2,"none"],[41,234,156,0,false,false,[22],2,"cobweb"],[42,564,156,0,false,false,[23],2,"cobweb"],[43,309,111,0,true,true,[30,24,22,18],2,"cobweb"],[44,309,231,0,true,true,[30,29,22,20],2,"cobweb"],[45,399,111,0,true,true,[31,26],2,"cobweb"],[46,489,111,0,true,true,[32,25,23,19],2,"cobweb"],[47,399,231,0,true,true,[31,28],2,"cobweb"],[48,489,231,0,true,true,[32,27,23,21],2,"cobweb"],[49,69,51,0,false,false,[33],3,"none"],[50,729,51,0,false,false,[35],3,"none"],[51,69,261,0,false,false,[34],3,"none"],[52,729,261,0,false,false,[36],3,"none"],[53,219,51,0,false,false,[41,37],3,"none"],[54,579,51,0,false,false,[42,38],3,"none"],[55,219,261,0,false,false,[41,39],3,"none"],[56,579,261,0,false,false,[42,40],3,"none"],[57,249,171,90,false,false,[44,43,41],3,"none"],[58,549,171,-90,false,false,[48,46,42],3,"none"],[59,354,171,0,true,true,[47,45,44,43],3,"wood"],[60,444,171,0,true,true,[48,47,46,45],3,"wood"],[61,84,66,0,false,false,[49],4,"none"],[62,84,246,0,false,false,[51],4,"none"],[63,714,66,0,false,false,[50],4,"none"],[64,714,246,0,false,false,[52],4,"none"],[65,204,66,0,false,false,[53],4,"none"],[66,594,66,0,false,false,[54],4,"none"],[67,204,246,0,false,false,[57,55],4,"none"],[68,594,246,0,false,false,[58,56],4,"none"],[69,249,156,90,false,false,[57],4,"none"],[70,549,156,-90,false,false,[58],4,"none"],[71,99,81,0,false,false,[61],5,"none"],[72,99,231,0,false,false,[62],5,"none"],[73,699,81,0,false,false,[63],5,"none"],[74,699,231,0,false,false,[64],5,"none"],[75,189,81,0,false,false,[69,65],5,"none"],[76,609,81,0,false,false,[70,66],5,"none"],[77,189,231,0,false,false,[69,67],5,"none"],[78,609,231,0,false,false,[70,68],5,"none"],[79,654,96,-90,true,true,[76,73],6,"none"],[80,654,216,-90,true,true,[78,74],6,"none"],[81,144,96,90,true,true,[75,71],6,"none"],[82,144,216,90,true,true,[77,72],6,"none"]],"tasks":[0,4]}